LICENSE
MANIFEST.in
README.md
setup.py
libpythonpro_valmeida90/__init__.py
libpythonpro_valmeida90/github_api.py
libpythonpro_valmeida90.egg-info/PKG-INFO
libpythonpro_valmeida90.egg-info/SOURCES.txt
libpythonpro_valmeida90.egg-info/dependency_links.txt
libpythonpro_valmeida90.egg-info/not-zip-safe
libpythonpro_valmeida90.egg-info/requires.txt
libpythonpro_valmeida90.egg-info/top_level.txt